mcp_google_cse/__init__.py
mcp_google_cse/__main__.py
mcp_google_cse/server.py
iflow_mcp_mcp_google_cse-0.1.4.dist-info/METADATA
iflow_mcp_mcp_google_cse-0.1.4.dist-info/WHEEL
iflow_mcp_mcp_google_cse-0.1.4.dist-info/entry_points.txt
iflow_mcp_mcp_google_cse-0.1.4.dist-info/licenses/LICENSE
iflow_mcp_mcp_google_cse-0.1.4.dist-info/RECORD
