Metadata-Version: 2.4
Name: iflow-mcp_mcp-google-cse
Version: 0.1.4
Summary: An MCP server for searching a custom Google search engine.
Project-URL: Homepage, https://github.com/Richard-Weiss/mcp-google-cse
Project-URL: Issues, https://github.com/Richard-Weiss/mcp-google-cse/issues
Author-email: Richard-Weiss <76665424+Richard-Weiss@users.noreply.github.com>
License-Expression: Unlicense
License-File: LICENSE
Keywords: Google CSE,Google Custom Search Engine,MCP,Model Context Protocol,Web Browsing
Classifier: Development Status :: 3 - Alpha
Classifier: Operating System :: OS Independent
Classifier: Programming Language :: Python :: 3
Classifier: Programming Language :: Python :: 3.11
Classifier: Programming Language :: Python :: 3.12
Requires-Python: >=3.11
Requires-Dist: google-api-python-client>=2.159.0
Requires-Dist: mcp>=1.2.0
